syncfit/__init__.py
syncfit/_version.py
syncfit/mcmc.py
syncfit/analysis/__init__.py
syncfit/analysis/equipartition.py
syncfit/analysis/plotter.py
syncfit/analysis/util.py
syncfit/models/Constants.py
syncfit/models/__init__.py
syncfit/models/b1b2_b3b4_weighted_model.py
syncfit/models/b1b2_model.py
syncfit/models/b4b5_model.py
syncfit/models/b4b5b3_model.py
syncfit/models/b5_model.py
syncfit/models/b5b3_model.py
syncfit/models/mq_model.py
syncfit/models/syncfit_model.py
syncfit/models/thermal_util.py
syncfit-0.3.4.dist-info/LICENSE
syncfit-0.3.4.dist-info/METADATA
syncfit-0.3.4.dist-info/WHEEL
syncfit-0.3.4.dist-info/top_level.txt
syncfit-0.3.4.dist-info/RECORD
