Metadata-Version: 2.1
Name: syncfit
Version: 0.3.4
Author-email: Noah Franz <nfranz@arizona.edu>, Collin Christy <collinchristy@arizona.edu>
License: MIT License
Project-URL: Home, https://github.com/alexander-group/syncfit
Classifier: License :: OSI Approved :: BSD License
Classifier: Topic :: Scientific/Engineering
Classifier: Intended Audience :: Science/Research
Classifier: Intended Audience :: Developers
Classifier: Operating System :: OS Independent
Classifier: License :: OSI Approved :: BSD License
Classifier: Programming Language :: Python
Classifier: Programming Language :: Python :: 3
Classifier: Programming Language :: Python :: 3.9
Classifier: Programming Language :: Python :: 3.10
Classifier: Programming Language :: Python :: 3.11
Classifier: Development Status :: 1 - Planning
Requires-Python: >=3.9
License-File: LICENSE
Requires-Dist: numpy >=1.20
Requires-Dist: matplotlib
Requires-Dist: scipy
Requires-Dist: astropy
Requires-Dist: emcee
Requires-Dist: dynesty
Provides-Extra: docs
Requires-Dist: syncfit ; extra == 'docs'
Requires-Dist: Sphinx ; extra == 'docs'
Requires-Dist: myst-parser ; extra == 'docs'
Requires-Dist: nbsphinx ; extra == 'docs'
Requires-Dist: sphinx-book-theme ; extra == 'docs'
Requires-Dist: sphinx-copybutton ; extra == 'docs'
Requires-Dist: autodoc ; extra == 'docs'
Requires-Dist: ipykernel ; extra == 'docs'
